gan_art/__init__.py
gan_art/GANArt.py
gan_art-0.1.4.dist-info/METADATA
gan_art-0.1.4.dist-info/WHEEL
gan_art-0.1.4.dist-info/RECORD
