Metadata-Version: 2.1
Name: gan-art
Version: 0.1.4
Summary: This package assists user to transfer style of images by training a GAN model.
Author: Elijah Yuan
Author-email: elijah.yuan6009@gmail.com
Requires-Python: >=3.9,<4.0
Classifier: Programming Language :: Python :: 3
Classifier: Programming Language :: Python :: 3.9
Classifier: Programming Language :: Python :: 3.10
Classifier: Programming Language :: Python :: 3.11
Classifier: Programming Language :: Python :: 3.12
